typerdrive/__init__.py
typerdrive/cloaked.py
typerdrive/config.py
typerdrive/constants.py
typerdrive/context.py
typerdrive/dirs.py
typerdrive/env.py
typerdrive/exceptions.py
typerdrive/format.py
typerdrive/handle_errors.py
typerdrive/model_parser.py
typerdrive/py.typed
typerdrive/types.py
typerdrive/version.py
typerdrive/cache/__init__.py
typerdrive/cache/attach.py
typerdrive/cache/commands.py
typerdrive/cache/exceptions.py
typerdrive/cache/manager.py
typerdrive/client/__init__.py
typerdrive/client/attach.py
typerdrive/client/base.py
typerdrive/client/exceptions.py
typerdrive/client/manager.py
typerdrive/logging/__init__.py
typerdrive/logging/attach.py
typerdrive/logging/commands.py
typerdrive/logging/exceptions.py
typerdrive/logging/manager.py
typerdrive/logging/utilities.py
typerdrive/settings/__init__.py
typerdrive/settings/attach.py
typerdrive/settings/commands.py
typerdrive/settings/exceptions.py
typerdrive/settings/manager.py
typerdrive/settings/utilities.py
typerdrive_demo/__init__.py
typerdrive_demo/attach_cache.py
typerdrive_demo/attach_client.py
typerdrive_demo/attach_settings.py
typerdrive_demo/cache_commands.py
typerdrive_demo/handle_errors.py
typerdrive_demo/helpers.py
typerdrive_demo/main.py
typerdrive_demo/settings_commands.py
typerdrive_demo/typerdrive_client.py
typerdrive-0.7.2.dist-info/METADATA
typerdrive-0.7.2.dist-info/WHEEL
typerdrive-0.7.2.dist-info/entry_points.txt
typerdrive-0.7.2.dist-info/licenses/LICENSE.md
typerdrive-0.7.2.dist-info/RECORD
