Metadata-Version: 2.4
Name: typerdrive
Version: 0.7.2
Summary: Develop API-Connected Typer Apps at Lightspeed
Project-URL: homepage, https://github.com/dusktreader/typerdrive
Project-URL: source, https://github.com/dusktreader/typerdrive
Project-URL: changelog, https://github.com/dusktreader/typerdrive/blob/main/CHANGELOG.md
Author-email: Tucker Beck <tucker.beck@gmail.com>
License-File: LICENSE.md
Requires-Python: <3.15,>=3.12
Requires-Dist: httpx~=0.28
Requires-Dist: humanize~=4.12
Requires-Dist: inflection~=0.5
Requires-Dist: loguru~=0.7
Requires-Dist: py-buzz~=7.3
Requires-Dist: pydantic~=2.11
Requires-Dist: pyperclip~=1.9
Requires-Dist: snick~=2.2
Requires-Dist: typer-repyt<0.9,>=0.8.1
Requires-Dist: typer~=0.15
Provides-Extra: demo
Requires-Dist: rich~=14.0; extra == 'demo'
